integrityguard/domain/ievi_score.py
integrityguard/domain/scan_result.py
integrityguard/domain/severity.py
integrityguard/interfaces/vulnerability_check.py
integrityguard/main.py
integrityguard/services/html_report_generator.py
integrityguard/services/ievi_calculator.py
integrityguard/templates/report.html
integrityguard/vulnerabilities/checkers/create_file_on_host_check.py
integrityguard/vulnerabilities/checkers/docker_group_check.py
integrityguard/vulnerabilities/checkers/elevate_privilege_check.py
integrityguard/vulnerabilities/checkers/etc_shadow_check.py
integrityguard/vulnerabilities/integrity_guard_tool.py
integrityguard_cli-1.1.3.dist-info/METADATA
integrityguard_cli-1.1.3.dist-info/WHEEL
integrityguard_cli-1.1.3.dist-info/entry_points.txt
integrityguard_cli-1.1.3.dist-info/RECORD
