Metadata-Version: 2.4
Name: integrityguard-cli
Version: 1.1.3
Summary: Tool to detect Privilege Escalation and Data Tampering risks in Docker environments
Author: lucascostamr812@gmail.com
Requires-Python: >=3.10
Classifier: Programming Language :: Python :: 3
Classifier: Programming Language :: Python :: 3.10
Classifier: Programming Language :: Python :: 3.11
Classifier: Programming Language :: Python :: 3.12
Classifier: Programming Language :: Python :: 3.13
Classifier: Programming Language :: Python :: 3.14
Requires-Dist: docker (>=7.1.0,<8.0.0)
Requires-Dist: jinja2 (>=3.1.6,<4.0.0)
